tigris/__init__.py
tigris/tigris.py
tigris/version.py
tigris-0.1.0.dist-info/LICENSE
tigris-0.1.0.dist-info/METADATA
tigris-0.1.0.dist-info/WHEEL
tigris-0.1.0.dist-info/entry_points.txt
tigris-0.1.0.dist-info/top_level.txt
tigris-0.1.0.dist-info/zip-safe
tigris-0.1.0.dist-info/RECORD
