Metadata-Version: 2.1
Name: tigris
Version: 0.1.0
Summary: Automating things with Python
Home-page: https://github.com/rdempsey/tigris
Author: Robert Dempsey
Author-email: robertonrails@gmail.com
License: MIT
Keywords: python,automation
Platform: UNKNOWN
Requires-Dist: click (>=7.0)
Provides-Extra: all
Requires-Dist: click (>=7.0) ; extra == 'all'
Requires-Dist: mock ; extra == 'all'
Requires-Dist: pytest ; extra == 'all'
Requires-Dist: pytest-cov ; extra == 'all'
Provides-Extra: docs
Requires-Dist: sphinx ; extra == 'docs'
Requires-Dist: mock ; extra == 'docs'
Requires-Dist: pytest ; extra == 'docs'
Requires-Dist: pytest-cov ; extra == 'docs'
Provides-Extra: lint
Requires-Dist: pep8 ; extra == 'lint'
Provides-Extra: test
Requires-Dist: mock ; extra == 'test'
Requires-Dist: pytest ; extra == 'test'
Requires-Dist: pytest-cov ; extra == 'test'
